[{"data":"2020-10-20T17:00:00","denominazione_provincia":"Varese","totale_casi":"6836","LOCALITA":"Varese","DATA":"20/10/2020","TMEDIA °C":"\"10\"","TMIN °C":"\"5\"","TMAX °C":"\"14\"","PUNTORUGIADA °C":"\"8\"","UMIDITA %":"\"88\"","VISIBILITA km":"\"16\"","VENTOMEDIA km/h":"\"6\"","VENTOMAX km/h":"\"11\"","RAFFICA km/h":"\"0\"","PRESSIONESLM mb":"\"1024\"","PRESSIONEMEDIA mb":"\"0\"","PIOGGIA mm":"\"0\"","FENOMENI\r":"\"Nebbia \"\r"},{"data":"2020-10-20T17:00:00","denominazione_provincia":"Como","totale_casi":"5673","LOCALITA":"Como","DATA":"20/10/2020","TMEDIA °C":"\"10\"","TMIN °C":"\"5\"","TMAX °C":"\"14\"","PUNTORUGIADA °C":"\"8\"","UMIDITA %":"\"88\"","VISIBILITA km":"\"16\"","VENTOMEDIA km/h":"\"6\"","VENTOMAX km/h":"\"11\"","RAFFICA km/h":"\"0\"","PRESSIONESLM mb":"\"1024\"","PRESSIONEMEDIA mb":"\"0\"","PIOGGIA mm":"\"0\"","FENOMENI\r":"\"Nebbia \"\r"},{"data":"2020-10-20T17:00:00","denominazione_provincia":"Sondrio","totale_casi":"1947","LOCALITA":"Albosaggia","DATA":"20/10/2020","TMEDIA °C":"\"11\"","TMIN °C":"\"7\"","TMAX °C":"\"14\"","PUNTORUGIADA °C":"\"8\"","UMIDITA %":"\"82\"","VISIBILITA km":"\"13\"","VENTOMEDIA km/h":"\"6\"","VENTOMAX km/h":"\"11\"","RAFFICA km/h":"\"0\"","PRESSIONESLM mb":"\"1024\"","PRESSIONEMEDIA mb":"\"0\"","PIOGGIA mm":"\"0\"","FENOMENI\r":"\"\"\r"},{"data":"2020-10-20T17:00:00","denominazione_provincia":"Milano","totale_casi":"40786","LOCALITA":"Milano","DATA":"20/10/2020","TMEDIA °C":"\"11\"","TMIN °C":"\"6\"","TMAX °C":"\"15\"","PUNTORUGIADA °C":"\"9\"","UMIDITA %":"\"87\"","VISIBILITA km":"\"14\"","VENTOMEDIA km/h":"\"3\"","VENTOMAX km/h":"\"8\"","RAFFICA km/h":"\"0\"","PRESSIONESLM mb":"\"1025\"","PRESSIONEMEDIA mb":"\"0\"","PIOGGIA mm":"\"0\"","FENOMENI\r":"\"Nebbia \"\r"},{"data":"2020-10-20T17:00:00","denominazione_provincia":"Bergamo","totale_casi":"16568","LOCALITA":"Bergamo","DATA":"20/10/2020","TMEDIA °C":"\"11\"","TMIN °C":"\"7\"","TMAX °C":"\"14\"","PUNTORUGIADA °C":"\"8\"","UMIDITA %":"\"82\"","VISIBILITA km":"\"13\"","VENTOMEDIA km/h":"\"6\"","VENTOMAX km/h":"\"11\"","RAFFICA km/h":"\"0\"","PRESSIONESLM mb":"\"1024\"","PRESSIONEMEDIA mb":"\"0\"","PIOGGIA mm":"\"0\"","FENOMENI\r":"\"\"\r"},{"data":"2020-10-20T17:00:00","denominazione_provincia":"Brescia","totale_casi":"18336","LOCALITA":"Brescia","DATA":"20/10/2020","TMEDIA °C":"\"11\"","TMIN °C":"\"7\"","TMAX °C":"\"14\"","PUNTORUGIADA °C":"\"8\"","UMIDITA %":"\"85\"","VISIBILITA km":"\"3\"","VENTOMEDIA km/h":"\"4\"","VENTOMAX km/h":"\"8\"","RAFFICA km/h":"\"0\"","PRESSIONESLM mb":"\"1024\"","PRESSIONEMEDIA mb":"\"0\"","PIOGGIA mm":"\"0\"","FENOMENI\r":"\"\"\r"},{"data":"2020-10-20T17:00:00","denominazione_provincia":"Pavia","totale_casi":"7249","LOCALITA":"Pavia","DATA":"20/10/2020","TMEDIA °C":"\"11\"","TMIN °C":"\"6\"","TMAX °C":"\"15\"","PUNTORUGIADA °C":"\"9\"","UMIDITA %":"\"87\"","VISIBILITA km":"\"14\"","VENTOMEDIA km/h":"\"3\"","VENTOMAX km/h":"\"8\"","RAFFICA km/h":"\"0\"","PRESSIONESLM mb":"\"1025\"","PRESSIONEMEDIA mb":"\"0\"","PIOGGIA mm":"\"0\"","FENOMENI\r":"\"Nebbia \"\r"},{"data":"2020-10-20T17:00:00","denominazione_provincia":"Cremona","totale_casi":"7316","LOCALITA":"Cremona","DATA":"20/10/2020","TMEDIA °C":"\"13\"","TMIN °C":"\"7\"","TMAX °C":"\"15\"","PUNTORUGIADA °C":"\"12\"","UMIDITA %":"\"96\"","VISIBILITA km":"\"12\"","VENTOMEDIA km/h":"\"5\"","VENTOMAX km/h":"\"13\"","RAFFICA km/h":"\"0\"","PRESSIONESLM mb":"\"1024\"","PRESSIONEMEDIA mb":"\"0\"","PIOGGIA mm":"\"0\"","FENOMENI\r":"\"\"\r"},{"data":"2020-10-20T17:00:00","denominazione_provincia":"Mantova","totale_casi":"4687","LOCALITA":"Mantova","DATA":"20/10/2020","TMEDIA °C":"\"11\"","TMIN °C":"\"6\"","TMAX °C":"\"16\"","PUNTORUGIADA °C":"\"9\"","UMIDITA %":"\"86\"","VISIBILITA km":"\"5\"","VENTOMEDIA km/h":"\"5\"","VENTOMAX km/h":"\"8\"","RAFFICA km/h":"\"0\"","PRESSIONESLM mb":"\"1024\"","PRESSIONEMEDIA mb":"\"0\"","PIOGGIA mm":"\"0\"","FENOMENI\r":"\"Nebbia \"\r"},{"data":"2020-10-20T17:00:00","denominazione_provincia":"Lecco","totale_casi":"3663","LOCALITA":"Lecco","DATA":"20/10/2020","TMEDIA °C":"\"11\"","TMIN °C":"\"7\"","TMAX °C":"\"14\"","PUNTORUGIADA °C":"\"8\"","UMIDITA %":"\"82\"","VISIBILITA km":"\"13\"","VENTOMEDIA km/h":"\"6\"","VENTOMAX km/h":"\"11\"","RAFFICA km/h":"\"0\"","PRESSIONESLM mb":"\"1024\"","PRESSIONEMEDIA mb":"\"0\"","PIOGGIA mm":"\"0\"","FENOMENI\r":"\"\"\r"},{"data":"2020-10-20T17:00:00","denominazione_provincia":"Lodi","totale_casi":"4260","LOCALITA":"Secugnago","DATA":"20/10/2020","TMEDIA °C":"\"13\"","TMIN °C":"\"7\"","TMAX °C":"\"15\"","PUNTORUGIADA °C":"\"12\"","UMIDITA %":"\"96\"","VISIBILITA km":"\"12\"","VENTOMEDIA km/h":"\"5\"","VENTOMAX km/h":"\"13\"","RAFFICA km/h":"\"0\"","PRESSIONESLM mb":"\"1024\"","PRESSIONEMEDIA mb":"\"0\"","PIOGGIA mm":"\"0\"","FENOMENI\r":"\"\"\r"},{"data":"2020-10-20T17:00:00","denominazione_provincia":"Monza e della Brianza","totale_casi":"9363","LOCALITA":"Monza","DATA":"20/10/2020","TMEDIA °C":"\"11\"","TMIN °C":"\"6\"","TMAX °C":"\"15\"","PUNTORUGIADA °C":"\"9\"","UMIDITA %":"\"87\"","VISIBILITA km":"\"14\"","VENTOMEDIA km/h":"\"3\"","VENTOMAX km/h":"\"8\"","RAFFICA km/h":"\"0\"","PRESSIONESLM mb":"\"1025\"","PRESSIONEMEDIA mb":"\"0\"","PIOGGIA mm":"\"0\"","FENOMENI\r":"\"Nebbia \"\r"},{"data":"2020-10-20T17:00:00","denominazione_provincia":"Monza","totale_casi":"1355"},{"data":"2020-10-20T17:00:00","denominazione_provincia":"Monza","totale_casi":"2440"}]